{
  "project_info": {
    "project_number": "198983271671",
    "project_id": "budget-fdab7",
    "storage_bucket": "budget-fdab7.appspot.com"
  },
  "client": [
    {
      "client_info": {
        "mobilesdk_app_id": "1:198983271671:android:749e95741c35b8e7ba3ff2",
        "android_client_info": {
          "package_name": "com.batsworks.budget"
        }
      },
      "oauth_client": [],
      "api_key": [
        {
          "current_key": "AIzaSyCG0VebkFFUEB0LNGy0jm-vTrfC47OCcoo"
        }
      ],
      "services": {
        "appinvite_service": {
          "other_platform_oauth_client": []
        }
      }
    }
  ],
  "configuration_version": "1"
}